Metadata-Version: 1.2
Name: my-opt
Version: 0.6.1
Summary: Asynchrone hyperparameter optimization
Home-page: http://github.com/NovaSyst/chocolate
Author: François-Michel De Rainville, Olivier Gagnon
Author-email: chocolate@novasyst.com
License: BSD 3-clauses
Keywords: AsynchroneHyperparameter Optimizer
Platform: UNKNOWN
Requires-Python: >=3
